InMemoryCloudDatastoreStub/__init__.py
InMemoryCloudDatastoreStub/_in_memory_store.py
InMemoryCloudDatastoreStub/_request_wrapper.py
InMemoryCloudDatastoreStub/_stored_object.py
InMemoryCloudDatastoreStub/_transactions.py
InMemoryCloudDatastoreStub/datastore_stub.py
InMemoryCloudDatastoreStub/futures.py
tests/__init__.py
tests/conftest.py
tests/models.py
tests/query_test.py
tests/transaction_test.py
InMemoryCloudDatastoreStub-0.0.15.dist-info/LICENSE.md
InMemoryCloudDatastoreStub-0.0.15.dist-info/METADATA
InMemoryCloudDatastoreStub-0.0.15.dist-info/WHEEL
InMemoryCloudDatastoreStub-0.0.15.dist-info/top_level.txt
InMemoryCloudDatastoreStub-0.0.15.dist-info/RECORD
