Metadata-Version: 2.1
Name: InMemoryCloudDatastoreStub
Version: 0.0.15
Summary: An in-memory stub implementation of Google Cloud Datastore for use in unit tests
Home-page: https://github.com/phil-lopreiato/google-cloud-datastore-stub/
License: UNKNOWN
Platform: UNKNOWN
Requires-Python: >=3
Requires-Dist: google-cloud-ndb (>1.2.1)
